README.rst
setup.py
infinite/__init__.py
infinite/gencacher.py
infinite/product.py
infinite.egg-info/PKG-INFO
infinite.egg-info/SOURCES.txt
infinite.egg-info/dependency_links.txt
infinite.egg-info/top_level.txt