Metadata-Version: 1.0
Name: infinite
Version: 0.1
Summary: itertools operations on infinite generators.
Home-page: http://github.com/enricobacis/infinite
Author: Enrico Bacis
Author-email: enrico.bacis@gmail.com
License: MIT
Keywords: infinite itertools product generators infinity
Platform: UNKNOWN
